ormir_mids/__init__.py
ormir_mids/dcm2omids.py
ormir_mids/config/__init__.py
ormir_mids/config/tag_definitions.py
ormir_mids/converters/__init__.py
ormir_mids/converters/abstract_converter.py
ormir_mids/converters/converter_template.py
ormir_mids/converters/cr.py
ormir_mids/converters/ct.py
ormir_mids/converters/dess_ge.py
ormir_mids/converters/dess_siemens.py
ormir_mids/converters/megre_ge.py
ormir_mids/converters/megre_philips.py
ormir_mids/converters/megre_siemens.py
ormir_mids/converters/mese_ge.py
ormir_mids/converters/mese_philips.py
ormir_mids/converters/mese_siemens.py
ormir_mids/converters/quantitative_maps.py
ormir_mids/utils/OMidsMedVolume.py
ormir_mids/utils/__init__.py
ormir_mids/utils/headers.py
ormir_mids/utils/image.py
ormir_mids/utils/io.py
ormir_mids-0.1.3.dist-info/licenses/LICENSE
ormir_mids-0.1.3.dist-info/METADATA
ormir_mids-0.1.3.dist-info/WHEEL
ormir_mids-0.1.3.dist-info/entry_points.txt
ormir_mids-0.1.3.dist-info/top_level.txt
ormir_mids-0.1.3.dist-info/RECORD
