Metadata-Version: 2.4
Name: ormir-mids
Version: 0.1.3
Summary: Library for standardized data input/output for musculoskeletal imaging, based on BIDS
Home-page: https://github.com/ormir-mids/ormir-mids
Author: ORMIR Contributors, Francesco Santini (maintainer)
Author-email: francesco.santini@unibas.ch
Project-URL: Bug Tracker, https://github.com/ormir-mids/ormir-mids/issuesleproject/issues
Classifier: Programming Language :: Python :: 3
Classifier: License :: OSI Approved :: Apache Software License
Classifier: Operating System :: OS Independent
Requires-Python: >=3.6
License-File: LICENSE
Requires-Dist: bidict
Requires-Dist: scipy
Requires-Dist: ormir-pyvoxel
Provides-Extra: test
Requires-Dist: pytest; extra == "test"
Requires-Dist: zenodo-get==1.6.1; extra == "test"
Dynamic: license-file
